schema/__init__.py
schema/schema_base_config.py
schema/schema_qp.py
schema/utils.py
schema_learn-0.2.dist-info/LICENSE
schema_learn-0.2.dist-info/METADATA
schema_learn-0.2.dist-info/WHEEL
schema_learn-0.2.dist-info/top_level.txt
schema_learn-0.2.dist-info/RECORD
