Metadata-Version: 2.1
Name: schema-learn
Version: 0.2
Summary: Framework for integrating heterogeneous modalities of data
Home-page: http://github.com/rs239/schema
Author: Rohit Singh
Author-email: rsingh@alum.mit.edu
License: MIT
License-File: LICENSE
Requires-Dist: numpy
Requires-Dist: scipy
Requires-Dist: pandas
Requires-Dist: scikit-learn
Requires-Dist: cvxopt
